langidentification/__init__.py
langidentification/langidentification.py
langidentification-1.2.dist-info/LICENSE
langidentification-1.2.dist-info/METADATA
langidentification-1.2.dist-info/WHEEL
langidentification-1.2.dist-info/top_level.txt
langidentification-1.2.dist-info/RECORD
