Metadata-Version: 2.1
Name: langidentification
Version: 1.2
Summary: A package for language identification based on fastText, including romanised South Asian languages and Arabic
Home-page: https://github.com/absu5530/langidentification
Author: Abhishek Suresh
Author-email: abhishek.sures@gmail.com
License: UNKNOWN
Platform: UNKNOWN
Classifier: Programming Language :: Python :: 3.9
Classifier: License :: OSI Approved :: GNU General Public License v3 (GPLv3)
License-File: LICENSE
Requires-Dist: fasttext (>=0.9.2)
Requires-Dist: wget (>=3.2)
